<annotation>
	<folder>JPEGImage</folder>
	<filename>000825.jpg</filename>
	<path>C:\Users\dell\Desktop\马帅700_1400\JPEGImage\000825.jpg</path>
	<source>
		<database>Unknown</database>
	</source>
	<size>
		<width>720</width>
		<height>720</height>
		<depth>3</depth>
	</size>
	<segmented>0</segmented>
	<object>
		<name>handsmoke</name>
		<pose>Unspecified</pose>
		<truncated>0</truncated>
		<difficult>0</difficult>
		<bndbox>
			<xmin>385</xmin>
			<ymin>257</ymin>
			<xmax>434</xmax>
			<ymax>318</ymax>
		</bndbox>
	</object>
	<object>
		<name>mouthwithoutsmoke</name>
		<pose>Unspecified</pose>
		<truncated>0</truncated>
		<difficult>0</difficult>
		<bndbox>
			<xmin>403</xmin>
			<ymin>85</ymin>
			<xmax>496</xmax>
			<ymax>212</ymax>
		</bndbox>
	</object>
</annotation>
