<annotation>
	<folder>JPEGImage</folder>
	<filename>001300.jpg</filename>
	<path>C:\Users\dell\Desktop\马帅700_1400\JPEGImage\001300.jpg</path>
	<source>
		<database>Unknown</database>
	</source>
	<size>
		<width>720</width>
		<height>720</height>
		<depth>3</depth>
	</size>
	<segmented>0</segmented>
	<object>
		<name>handsmoke</name>
		<pose>Unspecified</pose>
		<truncated>0</truncated>
		<difficult>0</difficult>
		<bndbox>
			<xmin>440</xmin>
			<ymin>428</ymin>
			<xmax>504</xmax>
			<ymax>488</ymax>
		</bndbox>
	</object>
	<object>
		<name>handwithoutsmoke</name>
		<pose>Unspecified</pose>
		<truncated>0</truncated>
		<difficult>0</difficult>
		<bndbox>
			<xmin>382</xmin>
			<ymin>145</ymin>
			<xmax>437</xmax>
			<ymax>203</ymax>
		</bndbox>
	</object>
	<object>
		<name>mouthwithoutsmoke</name>
		<pose>Unspecified</pose>
		<truncated>0</truncated>
		<difficult>0</difficult>
		<bndbox>
			<xmin>277</xmin>
			<ymin>51</ymin>
			<xmax>383</xmax>
			<ymax>211</ymax>
		</bndbox>
	</object>
</annotation>
