<annotation>
	<folder>JPEGImage</folder>
	<filename>001680.jpg</filename>
	<path>C:\Users\lenovo\Desktop\VOC2007\JPEGImage\001680.jpg</path>
	<source>
		<database>Unknown</database>
	</source>
	<size>
		<width>720</width>
		<height>720</height>
		<depth>3</depth>
	</size>
	<segmented>0</segmented>
	<object>
		<name>handsmoke</name>
		<pose>Unspecified</pose>
		<truncated>0</truncated>
		<difficult>0</difficult>
		<bndbox>
			<xmin>494</xmin>
			<ymin>385</ymin>
			<xmax>568</xmax>
			<ymax>449</ymax>
		</bndbox>
	</object>
	<object>
		<name>mouthwithoutsmoke</name>
		<pose>Unspecified</pose>
		<truncated>0</truncated>
		<difficult>0</difficult>
		<bndbox>
			<xmin>369</xmin>
			<ymin>62</ymin>
			<xmax>499</xmax>
			<ymax>225</ymax>
		</bndbox>
	</object>
</annotation>
