<annotation>
	<folder>JPEGImage</folder>
	<filename>004793.jpg</filename>
	<path>C:\Users\asus\Desktop\胡飞虹4001_5000\JPEGImage\004793.jpg</path>
	<source>
		<database>Unknown</database>
	</source>
	<size>
		<width>720</width>
		<height>720</height>
		<depth>3</depth>
	</size>
	<segmented>0</segmented>
	<object>
		<name>handwithoutsmoke</name>
		<pose>Unspecified</pose>
		<truncated>0</truncated>
		<difficult>0</difficult>
		<bndbox>
			<xmin>221</xmin>
			<ymin>417</ymin>
			<xmax>259</xmax>
			<ymax>436</ymax>
		</bndbox>
	</object>
	<object>
		<name>mouthsmoke</name>
		<pose>Unspecified</pose>
		<truncated>0</truncated>
		<difficult>0</difficult>
		<bndbox>
			<xmin>205</xmin>
			<ymin>7</ymin>
			<xmax>308</xmax>
			<ymax>130</ymax>
		</bndbox>
	</object>
</annotation>
