<annotation>
	<folder>JPEGImage</folder>
	<filename>005890.jpg</filename>
	<path>C:\Users\lenovo\Desktop\何国行5001_6099\JPEGImage\005890.jpg</path>
	<source>
		<database>Unknown</database>
	</source>
	<size>
		<width>720</width>
		<height>720</height>
		<depth>3</depth>
	</size>
	<segmented>0</segmented>
	<object>
		<name>mouthwithoutsmoke</name>
		<pose>Unspecified</pose>
		<truncated>0</truncated>
		<difficult>0</difficult>
		<bndbox>
			<xmin>241</xmin>
			<ymin>351</ymin>
			<xmax>374</xmax>
			<ymax>472</ymax>
		</bndbox>
	</object>
	<object>
		<name>mouthwithoutsmoke</name>
		<pose>Unspecified</pose>
		<truncated>1</truncated>
		<difficult>0</difficult>
		<bndbox>
			<xmin>631</xmin>
			<ymin>88</ymin>
			<xmax>720</xmax>
			<ymax>247</ymax>
		</bndbox>
	</object>
	<object>
		<name>handsmoke</name>
		<pose>Unspecified</pose>
		<truncated>0</truncated>
		<difficult>0</difficult>
		<bndbox>
			<xmin>668</xmin>
			<ymin>366</ymin>
			<xmax>713</xmax>
			<ymax>417</ymax>
		</bndbox>
	</object>
	<object>
		<name>handwithoutsmoke</name>
		<pose>Unspecified</pose>
		<truncated>0</truncated>
		<difficult>0</difficult>
		<bndbox>
			<xmin>474</xmin>
			<ymin>640</ymin>
			<xmax>497</xmax>
			<ymax>657</ymax>
		</bndbox>
	</object>
</annotation>
